{
  "report_id": "2026-W24",
  "year": 2026,
  "week": 24,
  "generated_at": "2026-06-16T12:38:15.619672",
  "article_count": 5,
  "articles": [
    {
      "article_id": "cb9d016c992d",
      "title": "廖岷出席亚太经合组织财政高官会并致辞",
      "source": "财政部",
      "source_type": "官方",
      "platform": "www.mof.gov.cn",
      "url": "http://www.mof.gov.cn/zhengwuxinxi/tupianxinwen1/202606/t20260612_3991523.htm",
      "content": "廖岷出席亚太经合组织财政高官会并致辞 EN 热门检索： 财政收支 积极财政政策 减税降费 首页 职能机构 新闻报道 信息公开 政务服务 交流互动 专题专栏 首页 职能机构 新闻报道 信息公开 政务服务 交流互动 专题专栏 财政视频 您现在的位置： 首页 > 新闻报道 > 图片报道 廖岷出席亚太经合组织财政高官会并致辞 发布日期：2026年06月12日 分享到微信朋友圈 x 打开微信，点击底部的“发现”， 使用“扫一扫”即可将网页分享至朋友圈。 2026年6月12日 来源：国际经济关系司 2026年6月11日至12日，财政部在四川成都举办亚太经合组织（APEC）财政高官会，财政部副部长廖岷出席会议并致开幕辞。 &nbsp; 廖岷表示，在科技进步和数字化转型驱动下，亚太地区经济保持快速增长，依然是全球经济的重要引擎。当前区域经济面临多重挑战，APEC经济体应坚持多边主义，深化宏观经济政策沟通协调，加快推进经济转型，维护区域产业链供应链稳定畅通，共同推动亚太经济长期可持续增长。 &nbsp; 廖岷还介绍了中国经济运行情况，强调在“十五五”时期，中国将持续推动高质量发展和高水平开放，进一步扩大内需、提振消费，与世界共享中国发展机遇和红利，共建亚太命运共同体。 &nbsp; 会议围绕全球和区域经济金融形势、支持民生发展的财政政策、数字基础设施融资、普惠金融和促进APEC青年财经人才交流合作等议题进行了深入讨论。各方高度肯定中国作为今年APEC东道主所发挥的引领作用，积极评价财金渠道取得的进展。6月10日，财政部还分别与亚洲基础设施投资银行、亚洲开发银行联合举办了数字基础设施融资和普惠金融专题研讨会，取得良好效果。&nbsp; &nbsp; 附件下载： 相关文章： 【 大 中 小 】 【打印此页】 【关闭窗口】 网站地图 联系我们 主办单位：中华人民共和国财政部 网站标识码：bm14000001&nbsp;&nbsp; 京ICP备05002860号 &nbsp;&nbsp; 京公网安备11010202000006号 技术支持：财政部信息网络中心 中华人民共和国财政部&nbsp;&nbsp;版权所有，如需转载，请注明来源 财政部微信 财政部视频号 财政部 官方抖音号 财政部 官方抖音号 移动客户端 Android下载 移动客户端 iphone下载",
      "summary": "廖岷出席亚太经合组织财政高官会并致辞 EN 热门检索： 财政收支 积极财政政策 减税降费 首页 职能机构 新闻报道 信息公开 政务服务 交流互动 专题专栏 首页 职能机构 新闻报道 信息公开 政务服务 交流互动 专题专栏 财政视频 您现在的位置： 首页 > 新闻报道 > 图片报道 廖岷出席亚太经合组织财政高官会并致辞 发布日期：2026年06月12日 分享到微信朋友圈 x 打开微信，点击底部的“发",
      "published_date": "2026-06-11",
      "collected_at": "2026-06-16T12:36:55.934048",
      "analysis": {
        "category": "其他",
        "sentiment_score": 0.6,
        "sentiment_label": "积极",
        "keywords": [
          "亚太经合组织",
          "财政高官会",
          "高质量发展",
          "扩大内需",
          "数字基础设施融资"
        ],
        "brief_summary": "廖岷出席APEC财政高官会并致辞",
        "entities": {
          "departments": [
            "财政部"
          ],
          "amounts": [],
          "tools": [],
          "people": [
            "廖岷"
          ]
        }
      }
    },
    {
      "article_id": "476b5039b4d6",
      "title": "财政部召开2027年中央部门预算编制工作动员会",
      "source": "财政部",
      "source_type": "官方",
      "platform": "www.mof.gov.cn",
      "url": "http://www.mof.gov.cn/zhengwuxinxi/tupianxinwen1/202606/t20260610_3991435.htm",
      "content": "财政部召开2027年中央部门预算编制工作动员会 EN 热门检索： 财政收支 积极财政政策 减税降费 首页 职能机构 新闻报道 信息公开 政务服务 交流互动 专题专栏 首页 职能机构 新闻报道 信息公开 政务服务 交流互动 专题专栏 财政视频 您现在的位置： 首页 > 新闻报道 > 图片报道 财政部召开2027年中央部门预算编制工作动员会 发布日期：2026年06月10日 分享到微信朋友圈 x 打开微信，点击底部的“发现”， 使用“扫一扫”即可将网页分享至朋友圈。 2026年6月10日 来源：预算司 2026年6月3日，财政部召开2027年中央部门预算编制工作动员会，总结过去一年部门预算管理工作进展，部署2027年中央部门预算编制工作。财政部党组成员、副部长宋其超同志出席会议并作动员讲话。中直管理局、文化和旅游部、市场监管总局和国家医保局的财务部门主要负责同志作了交流发言。全国人大常委会预算工委、审计署有关同志应邀出席会议。各中央预算单位财务部门、财政部相关司局负责同志参加会议。&nbsp; &nbsp; 附件下载： 相关文章： 【 大 中 小 】 【打印此页】 【关闭窗口】 网站地图 联系我们 主办单位：中华人民共和国财政部 网站标识码：bm14000001&nbsp;&nbsp; 京ICP备05002860号 &nbsp;&nbsp; 京公网安备11010202000006号 技术支持：财政部信息网络中心 中华人民共和国财政部&nbsp;&nbsp;版权所有，如需转载，请注明来源 财政部微信 财政部视频号 财政部 官方抖音号 财政部 官方抖音号 移动客户端 Android下载 移动客户端 iphone下载",
      "summary": "财政部召开2027年中央部门预算编制工作动员会 EN 热门检索： 财政收支 积极财政政策 减税降费 首页 职能机构 新闻报道 信息公开 政务服务 交流互动 专题专栏 首页 职能机构 新闻报道 信息公开 政务服务 交流互动 专题专栏 财政视频 您现在的位置： 首页 > 新闻报道 > 图片报道 财政部召开2027年中央部门预算编制工作动员会 发布日期：2026年06月10日 分享到微信朋友圈 x 打开",
      "published_date": "2026-06-10",
      "collected_at": "2026-06-16T12:36:56.098500",
      "analysis": {
        "category": "财政改革",
        "sentiment_score": 0.2,
        "sentiment_label": "中性",
        "keywords": [
          "预算编制",
          "中央部门",
          "动员会",
          "财政管理",
          "2027年"
        ],
        "brief_summary": "部署2027年中央部门预算编制工作",
        "entities": {
          "departments": [
            "财政部",
            "中直管理局",
            "文化和旅游部",
            "市场监管总局",
            "国家医保局",
            "全国人大常委会预算工委",
            "审计署"
          ],
          "amounts": [],
          "tools": [],
          "people": [
            "宋其超"
          ]
        }
      }
    },
    {
      "article_id": "74e33baac957",
      "title": "黄金价格持续下跌，短期和长期会怎么走？|当前宏观经济形势与热点分析",
      "source": "B站",
      "source_type": "社交媒体",
      "platform": "bilibili.com",
      "url": "https://www.bilibili.com/video/BV1yUJ56vECi",
      "content": "黄金价格持续下跌，短期和长期会怎么走？|当前宏观经济形势与热点分析  标签:黄金价格,宏观经济,金融学,股市,原油,投资,财经,股票,金融,黄金",
      "summary": "黄金价格持续下跌，短期和长期会怎么走？|当前宏观经济形势与热点分析",
      "published_date": "2026-06-12",
      "collected_at": "2026-06-16T12:37:07.330131",
      "play": 77491,
      "analysis": {
        "category": "其他",
        "sentiment_score": 0.0,
        "sentiment_label": "中性",
        "keywords": [
          "黄金价格",
          "宏观经济",
          "金融学",
          "股市",
          "原油",
          "投资",
          "财经",
          "股票",
          "金融",
          "黄金"
        ],
        "brief_summary": "分析黄金价格下跌的短期与长期走势",
        "entities": {
          "departments": [],
          "amounts": [],
          "tools": [],
          "people": []
        }
      }
    },
    {
      "article_id": "fb63d4a3dad8",
      "title": "本周经济数据分析：工业物价由于原材料而飙升，消费物价由于能源温和通胀，美国通胀原地起飞，年末加息概率定价",
      "source": "B站",
      "source_type": "社交媒体",
      "platform": "bilibili.com",
      "url": "https://www.bilibili.com/video/BV1haJA62Etv",
      "content": "本周经济数据分析：工业物价由于原材料而飙升，消费物价由于能源温和通胀，美国通胀原地起飞，年末加息概率定价 各位请以自己逻辑为主 标签:万物研究所,工业,数据分析,基金,股市,投资,经济,物价,数据,股票",
      "summary": "本周经济数据分析：工业物价由于原材料而飙升，消费物价由于能源温和通胀，美国通胀原地起飞，年末加息概率定价",
      "published_date": "2026-06-14",
      "collected_at": "2026-06-16T12:37:15.190418",
      "play": 32466,
      "analysis": {
        "category": "其他",
        "sentiment_score": -0.3,
        "sentiment_label": "谨慎",
        "keywords": [
          "工业物价",
          "原材料",
          "消费物价",
          "能源通胀",
          "美国通胀"
        ],
        "brief_summary": "分析工业与消费物价及美国通胀",
        "entities": {
          "departments": [],
          "amounts": [],
          "tools": [],
          "people": []
        }
      }
    },
    {
      "article_id": "ee420d2aa8b0",
      "title": "【财经早餐】2026.06.14星期日",
      "source": "B站",
      "source_type": "社交媒体",
      "platform": "bilibili.com",
      "url": "https://www.bilibili.com/video/BV1NzJH6REb2",
      "content": "【财经早餐】2026.06.14星期日 中国政府债券余额首次突破百万亿元\n亚洲经济体面临严重油气短缺\n年内全国铁路发送旅客人次创新高\n内地买家在港购房量价同比齐增\nA股股民数量已超2.5亿\n鸡蛋批发均价处于近十年同期最高\n11部门发文推动新能源重卡应用\n北京科技型企业孵化器达133家\n《金融信息服务数据分类分级指南》印发\n美国两大AI巨头突发“利空”\n区域外贸交出优异“成绩单” \n官方整治“大字吸睛、小字免责”等广告\n燃油车退出乘用车月 标签:A股股民数量已超2.5亿,油气短缺,中国政府债券余额,早新闻,财经",
      "summary": "【财经早餐】2026.06.14星期日",
      "published_date": "2026-06-14",
      "collected_at": "2026-06-16T12:37:12.160001",
      "play": 1244,
      "analysis": {
        "category": "其他",
        "sentiment_score": 0.1,
        "sentiment_label": "中性",
        "keywords": [
          "中国政府债券余额",
          "油气短缺",
          "A股股民数量",
          "新能源重卡",
          "金融信息服务数据分类分级"
        ],
        "brief_summary": "多领域财经新闻汇总，无明确财政政策导向",
        "entities": {
          "departments": [],
          "amounts": [
            "百万亿元",
            "2.5亿"
          ],
          "tools": [],
          "people": []
        }
      }
    }
  ],
  "category_distribution": {
    "其他": 4,
    "财政改革": 1
  },
  "sentiment_summary": {
    "average_score": 0.12,
    "positive_count": 1,
    "neutral_count": 3,
    "cautious_count": 1
  },
  "all_keywords": [
    "亚太经合组织",
    "财政高官会",
    "黄金",
    "新能源重卡",
    "投资",
    "预算编制",
    "财经",
    "消费物价",
    "扩大内需",
    "中央部门",
    "股票",
    "能源通胀",
    "美国通胀",
    "原油",
    "金融信息服务数据分类分级",
    "2027年",
    "数字基础设施融资",
    "财政管理",
    "宏观经济",
    "中国政府债券余额",
    "油气短缺",
    "高质量发展",
    "股市",
    "金融学",
    "A股股民数量",
    "动员会",
    "工业物价",
    "黄金价格",
    "金融",
    "原材料"
  ],
  "weekly_insight": "**总体判断**：本周财政政策基调呈现“积极有为、审慎平衡”特征。核心信号来自廖岷副部长在APEC财政高官会上的表态，强调**中国将继续实施积极的财政政策，注重跨周期与逆周期调节的有机结合**，同时关注外部通胀输入风险。财政部启动2027年中央部门预算编制工作，标志着中期财政规划管理进入精细化阶段，释放出**强化预算约束与绩效导向**的明确信号。\n\n**重点领域**：一是国际财政协调领域，廖岷发言聚焦亚太区域供应链韧性及数字经济税收合作，暗示中国将更主动参与全球财政治理规则制定。二是预算管理改革，2027年预算编制动员会突出“零基预算”理念深化，要求各部门**打破基数依赖、优化支出结构**，为后续财政可持续性奠定制度基础。三是物价传导压力，本周数据显示工业品价格受原材料飙升推动上行，而消费端通胀温和，**PPI与CPI剪刀差扩大**可能挤压中下游企业利润，需警惕结构性通缩风险。\n\n**趋势展望**：下周重点关注财政部是否发布专项债加速发行的补充通知，以对冲外部需求走弱。同时，美国通胀超预期引发的加息预期可能加剧人民币汇率波动，**财政政策需预留应对跨境资本流动冲击的缓冲空间**。建议密切跟踪7月政治局会议对下半年财政节奏的定调。"
}